domainrules/__init__.py
domainrules/baserule.py
domainrules/describe.py
domainrules/domainemul.py
domainrules/fabric.py
domainrules/greendomain.py
domainrules/levenshtein.py
domainrules/numbers.py
domainrules/reddomin.py
domainrules/regexp.py
domainrules/subdomain.py
domainrules/substring.py
domainrules/symbol.py
domainrules/validators.py
domainrules-0.1.15.1.dist-info/LICENSE
domainrules-0.1.15.1.dist-info/WHEEL
domainrules-0.1.15.1.dist-info/METADATA
domainrules-0.1.15.1.dist-info/RECORD
