Metadata-Version: 2.1
Name: domainrules
Version: 0.1.15.1
Summary: Let's describe alowed rules!
Home-page: https://github.com/Svyat33/domain_rules
Author: Svyatoslav
Author-email: svyatka@gmail.com
Requires-Python: >=3.7
Classifier: License :: OSI Approved :: MIT License
Requires-Dist: pydantic>=1.8.1
Requires-Dist: levenshtein>=0.12.0
